{
  "accentColor": "{{appsmith.theme.colors.primaryColor}}",
  "animateLoading": true,
  "borderRadius": "{{appsmith.theme.borderRadius.appBorderRadius}}",
  "bottomRow": 55,
  "boxShadow": "{{appsmith.theme.boxShadow.appBoxShadow}}",
  "childStylesheet": {
    "button": {
      "borderRadius": "{{appsmith.theme.borderRadius.appBorderRadius}}",
      "boxShadow": "none",
      "buttonColor": "{{appsmith.theme.colors.primaryColor}}"
    },
    "iconButton": {
      "borderRadius": "{{appsmith.theme.borderRadius.appBorderRadius}}",
      "boxShadow": "none",
      "menuColor": "{{appsmith.theme.colors.primaryColor}}"
    },
    "menuButton": {
      "borderRadius": "{{appsmith.theme.borderRadius.appBorderRadius}}",
      "boxShadow": "none",
      "menuColor": "{{appsmith.theme.colors.primaryColor}}"
    }
  },
  "columnOrder": [
    "customColumn1",
    "enabled",
    "id",
    "branch",
    "name",
    "rtsp",
    "opening_time",
    "closing_time",
    "polygon_yellow",
    "polygon_green",
    "polygon_blue",
    "telegram_group",
    "telegram_topic"
  ],
  "columnSizeMap": {
    "status": 75,
    "step": 62,
    "task": 245
  },
  "columnUpdatedAt": 1747915117065,
  "columnWidthMap": {
    "branch": 111,
    "enabled": 92
  },
  "defaultPageSize": 0,
  "defaultSelectedRowIndex": "",
  "delimiter": ",",
  "derivedColumns": {
    "customColumn1": {
      "borderRadius": "0px",
      "boxShadow": "none",
      "buttonColor": "#DD4B34",
      "buttonLabel": "{{data_table.processedTableData.map((currentRow, currentIndex) => ( 'Delete'))}}",
      "buttonLabelColor": "#FFFFFF",
      "buttonStyle": "rgb(3, 179, 101)",
      "columnType": "button",
      "computedValue": "",
      "enableFilter": true,
      "enableSort": true,
      "id": "customColumn1",
      "index": 5,
      "isCellVisible": true,
      "isDerived": true,
      "isDisabled": false,
      "isVisible": true,
      "label": "Delete",
      "labelColor": "#FFFFFF",
      "menuColor": "#03B365",
      "onClick": "{{showModal('Delete_Modal')}}",
      "width": 150
    }
  },
  "displayName": "Table",
  "dynamicBindingPathList": [
    {
      "key": "tableData"
    },
    {
      "key": "derivedColumns.customColumn1.buttonLabel"
    },
    {
      "key": "accentColor"
    },
    {
      "key": "borderRadius"
    },
    {
      "key": "boxShadow"
    },
    {
      "key": "primaryColumns.id.computedValue"
    },
    {
      "key": "primaryColumns.branch.computedValue"
    },
    {
      "key": "primaryColumns.name.computedValue"
    },
    {
      "key": "primaryColumns.opening_time.computedValue"
    },
    {
      "key": "primaryColumns.closing_time.computedValue"
    },
    {
      "key": "primaryColumns.polygon_yellow.computedValue"
    },
    {
      "key": "primaryColumns.polygon_green.computedValue"
    },
    {
      "key": "primaryColumns.polygon_blue.computedValue"
    },
    {
      "key": "primaryColumns.rtsp.computedValue"
    },
    {
      "key": "primaryColumns.enabled.computedValue"
    },
    {
      "key": "primaryColumns.customColumn1.computedValue"
    },
    {
      "key": "primaryColumns.telegram_group.computedValue"
    },
    {
      "key": "primaryColumns.telegram_topic.computedValue"
    }
  ],
  "dynamicPropertyPathList": [
    {
      "key": "tableData"
    }
  ],
  "dynamicTriggerPathList": [
    {
      "key": "onPageChange"
    },
    {
      "key": "onSearchTextChanged"
    },
    {
      "key": "onSort"
    }
  ],
  "enableClientSideSearch": true,
  "enableServerSideFiltering": false,
  "hideCard": false,
  "horizontalAlignment": "LEFT",
  "iconSVG": "/static/media/icon.db8a9cbd.svg",
  "isLoading": false,
  "isSortable": true,
  "isVisible": "true",
  "isVisibleDownload": false,
  "isVisibleFilters": false,
  "isVisiblePagination": true,
  "isVisibleSearch": true,
  "key": "zba5qel0au",
  "label": "Data",
  "labelTextSize": "0.875rem",
  "leftColumn": 1,
  "onPageChange": "{{SelectQuery.run()}}",
  "onSearchTextChanged": "{{SelectQuery.run()}}",
  "onSort": "{{SelectQuery.run()}}",
  "parentColumnSpace": 16.3125,
  "parentId": "59rw5mx0bq",
  "parentRowSpace": 10,
  "primaryColumnId": "id",
  "primaryColumns": {
    "branch": {
      "alias": "branch",
      "allowCellWrapping": false,
      "allowSameOptionsInNewRow": true,
      "cellBackground": "",
      "columnType": "text",
      "computedValue": "{{data_table.processedTableData.map((currentRow, currentIndex) => ( currentRow[\"branch\"]))}}",
      "currencyCode": "USD",
      "decimals": 0,
      "enableFilter": true,
      "enableSort": true,
      "fontStyle": "",
      "horizontalAlignment": "LEFT",
      "id": "branch",
      "index": 1,
      "isCellEditable": false,
      "isCellVisible": true,
      "isDerived": false,
      "isDisabled": false,
      "isDiscardVisible": true,
      "isEditable": false,
      "isSaveVisible": true,
      "isVisible": true,
      "label": "Kód pobočky",
      "notation": "standard",
      "originalId": "branch",
      "sticky": "",
      "textColor": "",
      "textSize": "0.875rem",
      "thousandSeparator": true,
      "validation": {},
      "verticalAlignment": "CENTER",
      "width": 150
    },
    "closing_time": {
      "alias": "closing_time",
      "allowCellWrapping": false,
      "allowSameOptionsInNewRow": true,
      "cellBackground": "",
      "columnType": "text",
      "computedValue": "{{data_table.processedTableData.map((currentRow, currentIndex) => ( currentRow[\"closing_time\"]))}}",
      "currencyCode": "USD",
      "decimals": 0,
      "enableFilter": true,
      "enableSort": true,
      "fontStyle": "",
      "horizontalAlignment": "LEFT",
      "id": "closing_time",
      "index": 5,
      "isCellEditable": false,
      "isCellVisible": true,
      "isDerived": false,
      "isDisabled": false,
      "isDiscardVisible": true,
      "isEditable": false,
      "isSaveVisible": true,
      "isVisible": false,
      "label": "closing_time",
      "notation": "standard",
      "originalId": "closing_time",
      "sticky": "",
      "textColor": "",
      "textSize": "0.875rem",
      "thousandSeparator": true,
      "validation": {},
      "verticalAlignment": "CENTER",
      "width": 150
    },
    "customColumn1": {
      "alias": "Aktivní",
      "allowCellWrapping": false,
      "allowSameOptionsInNewRow": true,
      "buttonStyle": "rgb(3, 179, 101)",
      "columnType": "html",
      "computedValue": "{{(() => { const tableData = data_table.processedTableData || []; return tableData.length > 0 ? tableData.map((currentRow, currentIndex) => (currentRow.enabled ? '☑️' : '')) : currentRow.enabled ? '☑️' : '' })()}}",
      "currencyCode": "USD",
      "decimals": 0,
      "enableFilter": true,
      "enableSort": true,
      "horizontalAlignment": "LEFT",
      "id": "customColumn1",
      "index": 10,
      "isCellEditable": false,
      "isCellVisible": true,
      "isDerived": true,
      "isDisabled": false,
      "isDiscardVisible": true,
      "isEditable": false,
      "isSaveVisible": true,
      "isVisible": true,
      "label": "Aktivní",
      "labelColor": "#FFFFFF",
      "notation": "standard",
      "originalId": "customColumn1",
      "sticky": "",
      "textSize": "0.875rem",
      "thousandSeparator": true,
      "validation": {},
      "verticalAlignment": "CENTER",
      "width": 150
    },
    "enabled": {
      "alias": "enabled",
      "allowCellWrapping": false,
      "allowSameOptionsInNewRow": true,
      "cellBackground": "",
      "columnType": "switch",
      "computedValue": "{{(() => { const tableData = data_table.processedTableData || []; return tableData.length > 0 ? tableData.map((currentRow, currentIndex) => (currentRow.enabled)) : currentRow.enabled })()}}",
      "currencyCode": "USD",
      "decimals": 0,
      "enableFilter": true,
      "enableSort": true,
      "fontStyle": "",
      "horizontalAlignment": "LEFT",
      "id": "enabled",
      "index": 9,
      "isCellEditable": false,
      "isCellVisible": true,
      "isDerived": false,
      "isDisabled": false,
      "isDiscardVisible": true,
      "isEditable": false,
      "isSaveVisible": true,
      "isVisible": false,
      "label": "enabled",
      "notation": "standard",
      "originalId": "enabled",
      "sticky": "",
      "textColor": "",
      "textSize": "0.875rem",
      "thousandSeparator": true,
      "validation": {},
      "verticalAlignment": "CENTER",
      "width": 150
    },
    "id": {
      "alias": "id",
      "allowCellWrapping": false,
      "allowSameOptionsInNewRow": true,
      "cellBackground": "",
      "columnType": "number",
      "computedValue": "{{data_table.processedTableData.map((currentRow, currentIndex) => ( currentRow[\"id\"]))}}",
      "currencyCode": "USD",
      "decimals": 0,
      "enableFilter": true,
      "enableSort": true,
      "fontStyle": "",
      "horizontalAlignment": "LEFT",
      "id": "id",
      "index": 0,
      "isCellEditable": false,
      "isCellVisible": true,
      "isDerived": false,
      "isDisabled": false,
      "isDiscardVisible": true,
      "isEditable": false,
      "isSaveVisible": true,
      "isVisible": false,
      "label": "id",
      "notation": "standard",
      "originalId": "id",
      "sticky": "",
      "textColor": "",
      "textSize": "0.875rem",
      "thousandSeparator": true,
      "validation": {},
      "verticalAlignment": "CENTER",
      "width": 150
    },
    "name": {
      "alias": "name",
      "allowCellWrapping": false,
      "allowSameOptionsInNewRow": true,
      "cellBackground": "",
      "columnType": "text",
      "computedValue": "{{data_table.processedTableData.map((currentRow, currentIndex) => ( currentRow[\"name\"]))}}",
      "currencyCode": "USD",
      "decimals": 0,
      "enableFilter": true,
      "enableSort": true,
      "fontStyle": "",
      "horizontalAlignment": "LEFT",
      "id": "name",
      "index": 2,
      "isCellEditable": false,
      "isCellVisible": true,
      "isDerived": false,
      "isDisabled": false,
      "isDiscardVisible": true,
      "isEditable": false,
      "isSaveVisible": true,
      "isVisible": true,
      "label": "Název pobočky",
      "notation": "standard",
      "originalId": "name",
      "sticky": "",
      "textColor": "",
      "textSize": "0.875rem",
      "thousandSeparator": true,
      "validation": {},
      "verticalAlignment": "CENTER",
      "width": 150
    },
    "opening_time": {
      "alias": "opening_time",
      "allowCellWrapping": false,
      "allowSameOptionsInNewRow": true,
      "cellBackground": "",
      "columnType": "text",
      "computedValue": "{{data_table.processedTableData.map((currentRow, currentIndex) => ( currentRow[\"opening_time\"]))}}",
      "currencyCode": "USD",
      "decimals": 0,
      "enableFilter": true,
      "enableSort": true,
      "fontStyle": "",
      "horizontalAlignment": "LEFT",
      "id": "opening_time",
      "index": 4,
      "isCellEditable": false,
      "isCellVisible": true,
      "isDerived": false,
      "isDisabled": false,
      "isDiscardVisible": true,
      "isEditable": false,
      "isSaveVisible": true,
      "isVisible": false,
      "label": "opening_time",
      "notation": "standard",
      "originalId": "opening_time",
      "sticky": "",
      "textColor": "",
      "textSize": "0.875rem",
      "thousandSeparator": true,
      "validation": {},
      "verticalAlignment": "CENTER",
      "width": 150
    },
    "polygon_blue": {
      "alias": "polygon_blue",
      "allowCellWrapping": false,
      "allowSameOptionsInNewRow": true,
      "cellBackground": "",
      "columnType": "text",
      "computedValue": "{{data_table.processedTableData.map((currentRow, currentIndex) => ( currentRow[\"polygon_blue\"]))}}",
      "currencyCode": "USD",
      "decimals": 0,
      "enableFilter": true,
      "enableSort": true,
      "fontStyle": "",
      "horizontalAlignment": "LEFT",
      "id": "polygon_blue",
      "index": 8,
      "isCellEditable": false,
      "isCellVisible": true,
      "isDerived": false,
      "isDisabled": false,
      "isDiscardVisible": true,
      "isEditable": false,
      "isSaveVisible": true,
      "isVisible": false,
      "label": "polygon_blue",
      "notation": "standard",
      "originalId": "polygon_blue",
      "sticky": "",
      "textColor": "",
      "textSize": "0.875rem",
      "thousandSeparator": true,
      "validation": {},
      "verticalAlignment": "CENTER",
      "width": 150
    },
    "polygon_green": {
      "alias": "polygon_green",
      "allowCellWrapping": false,
      "allowSameOptionsInNewRow": true,
      "cellBackground": "",
      "columnType": "text",
      "computedValue": "{{data_table.processedTableData.map((currentRow, currentIndex) => ( currentRow[\"polygon_green\"]))}}",
      "currencyCode": "USD",
      "decimals": 0,
      "enableFilter": true,
      "enableSort": true,
      "fontStyle": "",
      "horizontalAlignment": "LEFT",
      "id": "polygon_green",
      "index": 7,
      "isCellEditable": false,
      "isCellVisible": true,
      "isDerived": false,
      "isDisabled": false,
      "isDiscardVisible": true,
      "isEditable": false,
      "isSaveVisible": true,
      "isVisible": false,
      "label": "polygon_green",
      "notation": "standard",
      "originalId": "polygon_green",
      "sticky": "",
      "textColor": "",
      "textSize": "0.875rem",
      "thousandSeparator": true,
      "validation": {},
      "verticalAlignment": "CENTER",
      "width": 150
    },
    "polygon_yellow": {
      "alias": "polygon_yellow",
      "allowCellWrapping": false,
      "allowSameOptionsInNewRow": true,
      "cellBackground": "",
      "columnType": "text",
      "computedValue": "{{data_table.processedTableData.map((currentRow, currentIndex) => ( currentRow[\"polygon_yellow\"]))}}",
      "currencyCode": "USD",
      "decimals": 0,
      "enableFilter": true,
      "enableSort": true,
      "fontStyle": "",
      "horizontalAlignment": "LEFT",
      "id": "polygon_yellow",
      "index": 6,
      "isCellEditable": false,
      "isCellVisible": true,
      "isDerived": false,
      "isDisabled": false,
      "isDiscardVisible": true,
      "isEditable": false,
      "isSaveVisible": true,
      "isVisible": false,
      "label": "polygon_yellow",
      "notation": "standard",
      "originalId": "polygon_yellow",
      "sticky": "",
      "textColor": "",
      "textSize": "0.875rem",
      "thousandSeparator": true,
      "validation": {},
      "verticalAlignment": "CENTER",
      "width": 150
    },
    "rtsp": {
      "alias": "rtsp",
      "allowCellWrapping": false,
      "allowSameOptionsInNewRow": true,
      "cellBackground": "",
      "columnType": "text",
      "computedValue": "{{data_table.processedTableData.map((currentRow, currentIndex) => ( currentRow[\"rtsp\"]))}}",
      "currencyCode": "USD",
      "decimals": 0,
      "enableFilter": true,
      "enableSort": true,
      "fontStyle": "",
      "horizontalAlignment": "LEFT",
      "id": "rtsp",
      "index": 8,
      "isCellEditable": false,
      "isCellVisible": true,
      "isDerived": false,
      "isDisabled": false,
      "isDiscardVisible": true,
      "isEditable": false,
      "isSaveVisible": true,
      "isVisible": false,
      "label": "RTSP",
      "notation": "standard",
      "originalId": "rtsp",
      "sticky": "",
      "textColor": "",
      "textSize": "0.875rem",
      "thousandSeparator": true,
      "validation": {},
      "verticalAlignment": "CENTER",
      "width": 150
    },
    "telegram_group": {
      "alias": "telegram_group",
      "allowCellWrapping": false,
      "allowSameOptionsInNewRow": true,
      "cellBackground": "",
      "columnType": "text",
      "computedValue": "{{data_table.processedTableData.map((currentRow, currentIndex) => ( currentRow[\"telegram_group\"]))}}",
      "currencyCode": "USD",
      "decimals": 0,
      "enableFilter": true,
      "enableSort": true,
      "fontStyle": "",
      "horizontalAlignment": "LEFT",
      "id": "telegram_group",
      "index": 9,
      "isCellEditable": false,
      "isCellVisible": true,
      "isDerived": false,
      "isDisabled": false,
      "isDiscardVisible": true,
      "isEditable": false,
      "isSaveVisible": true,
      "isVisible": true,
      "label": "TG Group",
      "notation": "standard",
      "originalId": "telegram_group",
      "sticky": "",
      "textColor": "",
      "textSize": "0.875rem",
      "thousandSeparator": true,
      "validation": {},
      "verticalAlignment": "CENTER",
      "width": 150
    },
    "telegram_topic": {
      "alias": "telegram_topic",
      "allowCellWrapping": false,
      "allowSameOptionsInNewRow": true,
      "cellBackground": "",
      "columnType": "text",
      "computedValue": "{{data_table.processedTableData.map((currentRow, currentIndex) => ( currentRow[\"telegram_topic\"]))}}",
      "currencyCode": "USD",
      "decimals": 0,
      "enableFilter": true,
      "enableSort": true,
      "fontStyle": "",
      "horizontalAlignment": "LEFT",
      "id": "telegram_topic",
      "index": 10,
      "isCellEditable": false,
      "isCellVisible": true,
      "isDerived": false,
      "isDisabled": false,
      "isDiscardVisible": true,
      "isEditable": false,
      "isSaveVisible": true,
      "isVisible": true,
      "label": "TG Topic",
      "notation": "standard",
      "originalId": "telegram_topic",
      "sticky": "",
      "textColor": "",
      "textSize": "0.875rem",
      "thousandSeparator": true,
      "validation": {},
      "verticalAlignment": "CENTER",
      "width": 150
    }
  },
  "renderMode": "CANVAS",
  "rightColumn": 64,
  "searchKey": "",
  "serverSidePaginationEnabled": true,
  "tableData": "{{SelectQuery.data}}",
  "textSize": "0.875rem",
  "topRow": 6,
  "totalRecordsCount": 0,
  "type": "TABLE_WIDGET_V2",
  "version": 3,
  "verticalAlignment": "CENTER",
  "widgetId": "uji69u6swx",
  "widgetName": "data_table"
}